setup.py
distributions9545/Binomialdistribution.py
distributions9545/Gaussiandistribution.py
distributions9545/Generaldistribution.py
distributions9545/__init__.py
distributions9545.egg-info/PKG-INFO
distributions9545.egg-info/SOURCES.txt
distributions9545.egg-info/dependency_links.txt
distributions9545.egg-info/not-zip-safe
distributions9545.egg-info/top_level.txt